LICENSE
README.md
setup.py
betting_models/__init__.py
betting_models/league_markets/__init__.py
betting_models/league_markets/dispatch.py
betting_models/league_markets/seeding_model.py
betting_models/match_markets/__init__.py
betting_models/match_markets/backsolve_lambda.py
betting_models/match_markets/config.py
betting_models/match_markets/dispatch.py
betting_models/match_markets/format_one.py
betting_models/match_markets/format_zero.py
betting_models/match_markets/market_model_base.py
betting_models/match_markets/score_model.py
football_betting_models.egg-info/PKG-INFO
football_betting_models.egg-info/SOURCES.txt
football_betting_models.egg-info/dependency_links.txt
football_betting_models.egg-info/requires.txt
football_betting_models.egg-info/top_level.txt